{
    "publisher": {
        "publisherId": "6dff7de5-d651-4dbc-82b1-5dc71aedb040",
        "publisherName": "NickScialli",
        "displayName": "Nick Scialli",
        "flags": "verified",
        "domain": null,
        "isDomainVerified": false
    },
    "extensionId": "78dd796f-7f32-4db0-8ea2-dd349997c152",
    "extensionName": "svelte-dark",
    "displayName": "Svelte Dark",
    "flags": "validated, public",
    "lastUpdated": "2021-02-16T13:17:20.127Z",
    "publishedDate": "2021-02-15T03:38:23.353Z",
    "releaseDate": "2021-02-15T03:38:23.353Z",
    "shortDescription": "A dark version of the Svelte framework color scheme",
    "versions": [
        {
            "version": "0.0.6",
            "flags": "validated",
            "lastUpdated": "2021-02-16T13:17:20.123Z",
            "files": [
                {
                    "assetType": "Microsoft.VisualStudio.Code.Manifest",
                    "source": "https://nickscialli.gallerycdn.vsassets.io/extensions/nickscialli/svelte-dark/0.0.6/1613481302410/Microsoft.VisualStudio.Code.Manifest"
                },
                {
                    "assetType": "Microsoft.VisualStudio.Services.Content.Changelog",
                    "source": "https://nickscialli.gallerycdn.vsassets.io/extensions/nickscialli/svelte-dark/0.0.6/1613481302410/Microsoft.VisualStudio.Services.Content.Changelog"
                },
                {
                    "assetType": "Microsoft.VisualStudio.Services.Content.Details",
                    "source": "https://nickscialli.gallerycdn.vsassets.io/extensions/nickscialli/svelte-dark/0.0.6/1613481302410/Microsoft.VisualStudio.Services.Content.Details"
                },
                {
                    "assetType": "Microsoft.VisualStudio.Services.Icons.Default",
                    "source": "https://nickscialli.gallerycdn.vsassets.io/extensions/nickscialli/svelte-dark/0.0.6/1613481302410/Microsoft.VisualStudio.Services.Icons.Default"
                },
                {
                    "assetType": "Microsoft.VisualStudio.Services.Icons.Small",
                    "source": "https://nickscialli.gallerycdn.vsassets.io/extensions/nickscialli/svelte-dark/0.0.6/1613481302410/Microsoft.VisualStudio.Services.Icons.Small"
                },
                {
                    "assetType": "Microsoft.VisualStudio.Services.VsixManifest",
                    "source": "https://nickscialli.gallerycdn.vsassets.io/extensions/nickscialli/svelte-dark/0.0.6/1613481302410/Microsoft.VisualStudio.Services.VsixManifest"
                },
                {
                    "assetType": "Microsoft.VisualStudio.Services.VSIXPackage",
                    "source": "https://nickscialli.gallerycdn.vsassets.io/extensions/nickscialli/svelte-dark/0.0.6/1613481302410/Microsoft.VisualStudio.Services.VSIXPackage"
                },
                {
                    "assetType": "Microsoft.VisualStudio.Services.VsixSignature",
                    "source": "https://nickscialli.gallerycdn.vsassets.io/extensions/nickscialli/svelte-dark/0.0.6/1613481302410/Microsoft.VisualStudio.Services.VsixSignature"
                }
            ],
            "properties": [
                {
                    "key": "Microsoft.VisualStudio.Services.Links.Getstarted",
                    "value": "https://github.com/nas5w/svelte-dark"
                },
                {
                    "key": "Microsoft.VisualStudio.Services.Links.Source",
                    "value": "https://github.com/nas5w/svelte-dark"
                },
                {
                    "key": "Microsoft.VisualStudio.Services.Links.GitHub",
                    "value": "https://github.com/nas5w/svelte-dark"
                },
                {
                    "key": "Microsoft.VisualStudio.Code.Engine",
                    "value": "^1.0.0"
                },
                {
                    "key": "Microsoft.VisualStudio.Services.GitHubFlavoredMarkdown",
                    "value": "true"
                },
                {
                    "key": "Microsoft.VisualStudio.Code.ExtensionDependencies",
                    "value": ""
                },
                {
                    "key": "Microsoft.VisualStudio.Code.ExtensionPack",
                    "value": ""
                },
                {
                    "key": "Microsoft.VisualStudio.Code.LocalizedLanguages",
                    "value": ""
                },
                {
                    "key": "Microsoft.VisualStudio.Code.ExtensionKind",
                    "value": "ui,workspace,web"
                }
            ],
            "assetUri": "https://nickscialli.gallerycdn.vsassets.io/extensions/nickscialli/svelte-dark/0.0.6/1613481302410",
            "fallbackAssetUri": "https://nickscialli.gallery.vsassets.io/_apis/public/gallery/publisher/NickScialli/extension/svelte-dark/0.0.6/assetbyname"
        },
        {
            "version": "0.0.5",
            "flags": "validated",
            "lastUpdated": "2021-02-15T15:17:58.377Z",
            "files": [
                {
                    "assetType": "Microsoft.VisualStudio.Code.Manifest",
                    "source": "https://nickscialli.gallerycdn.vsassets.io/extensions/nickscialli/svelte-dark/0.0.5/1613402140789/Microsoft.VisualStudio.Code.Manifest"
                },
                {
                    "assetType": "Microsoft.VisualStudio.Services.Content.Changelog",
                    "source": "https://nickscialli.gallerycdn.vsassets.io/extensions/nickscialli/svelte-dark/0.0.5/1613402140789/Microsoft.VisualStudio.Services.Content.Changelog"
                },
                {
                    "assetType": "Microsoft.VisualStudio.Services.Content.Details",
                    "source": "https://nickscialli.gallerycdn.vsassets.io/extensions/nickscialli/svelte-dark/0.0.5/1613402140789/Microsoft.VisualStudio.Services.Content.Details"
                },
                {
                    "assetType": "Microsoft.VisualStudio.Services.Icons.Default",
                    "source": "https://nickscialli.gallerycdn.vsassets.io/extensions/nickscialli/svelte-dark/0.0.5/1613402140789/Microsoft.VisualStudio.Services.Icons.Default"
                },
                {
                    "assetType": "Microsoft.VisualStudio.Services.Icons.Small",
                    "source": "https://nickscialli.gallerycdn.vsassets.io/extensions/nickscialli/svelte-dark/0.0.5/1613402140789/Microsoft.VisualStudio.Services.Icons.Small"
                },
                {
                    "assetType": "Microsoft.VisualStudio.Services.VsixManifest",
                    "source": "https://nickscialli.gallerycdn.vsassets.io/extensions/nickscialli/svelte-dark/0.0.5/1613402140789/Microsoft.VisualStudio.Services.VsixManifest"
                },
                {
                    "assetType": "Microsoft.VisualStudio.Services.VSIXPackage",
                    "source": "https://nickscialli.gallerycdn.vsassets.io/extensions/nickscialli/svelte-dark/0.0.5/1613402140789/Microsoft.VisualStudio.Services.VSIXPackage"
                }
            ],
            "properties": [
                {
                    "key": "Microsoft.VisualStudio.Services.Links.Getstarted",
                    "value": "https://github.com/nas5w/svelte-dark"
                },
                {
                    "key": "Microsoft.VisualStudio.Services.Links.Source",
                    "value": "https://github.com/nas5w/svelte-dark"
                },
                {
                    "key": "Microsoft.VisualStudio.Services.Links.GitHub",
                    "value": "https://github.com/nas5w/svelte-dark"
                },
                {
                    "key": "Microsoft.VisualStudio.Code.Engine",
                    "value": "^1.53.0"
                },
                {
                    "key": "Microsoft.VisualStudio.Services.GitHubFlavoredMarkdown",
                    "value": "true"
                },
                {
                    "key": "Microsoft.VisualStudio.Code.ExtensionDependencies",
                    "value": ""
                },
                {
                    "key": "Microsoft.VisualStudio.Code.ExtensionPack",
                    "value": ""
                },
                {
                    "key": "Microsoft.VisualStudio.Code.LocalizedLanguages",
                    "value": ""
                },
                {
                    "key": "Microsoft.VisualStudio.Code.ExtensionKind",
                    "value": "ui,workspace,web"
                }
            ],
            "assetUri": "https://nickscialli.gallerycdn.vsassets.io/extensions/nickscialli/svelte-dark/0.0.5/1613402140789",
            "fallbackAssetUri": "https://nickscialli.gallery.vsassets.io/_apis/public/gallery/publisher/NickScialli/extension/svelte-dark/0.0.5/assetbyname"
        },
        {
            "version": "0.0.4",
            "flags": "validated",
            "lastUpdated": "2021-02-15T04:19:15.887Z",
            "files": [
                {
                    "assetType": "Microsoft.VisualStudio.Code.Manifest",
                    "source": "https://nickscialli.gallerycdn.vsassets.io/extensions/nickscialli/svelte-dark/0.0.4/1613362617047/Microsoft.VisualStudio.Code.Manifest"
                },
                {
                    "assetType": "Microsoft.VisualStudio.Services.Content.Changelog",
                    "source": "https://nickscialli.gallerycdn.vsassets.io/extensions/nickscialli/svelte-dark/0.0.4/1613362617047/Microsoft.VisualStudio.Services.Content.Changelog"
                },
                {
                    "assetType": "Microsoft.VisualStudio.Services.Content.Details",
                    "source": "https://nickscialli.gallerycdn.vsassets.io/extensions/nickscialli/svelte-dark/0.0.4/1613362617047/Microsoft.VisualStudio.Services.Content.Details"
                },
                {
                    "assetType": "Microsoft.VisualStudio.Services.Icons.Default",
                    "source": "https://nickscialli.gallerycdn.vsassets.io/extensions/nickscialli/svelte-dark/0.0.4/1613362617047/Microsoft.VisualStudio.Services.Icons.Default"
                },
                {
                    "assetType": "Microsoft.VisualStudio.Services.Icons.Small",
                    "source": "https://nickscialli.gallerycdn.vsassets.io/extensions/nickscialli/svelte-dark/0.0.4/1613362617047/Microsoft.VisualStudio.Services.Icons.Small"
                },
                {
                    "assetType": "Microsoft.VisualStudio.Services.VsixManifest",
                    "source": "https://nickscialli.gallerycdn.vsassets.io/extensions/nickscialli/svelte-dark/0.0.4/1613362617047/Microsoft.VisualStudio.Services.VsixManifest"
                },
                {
                    "assetType": "Microsoft.VisualStudio.Services.VSIXPackage",
                    "source": "https://nickscialli.gallerycdn.vsassets.io/extensions/nickscialli/svelte-dark/0.0.4/1613362617047/Microsoft.VisualStudio.Services.VSIXPackage"
                }
            ],
            "properties": [
                {
                    "key": "Microsoft.VisualStudio.Services.Links.Getstarted",
                    "value": "https://github.com/nas5w/svelte-dark"
                },
                {
                    "key": "Microsoft.VisualStudio.Services.Links.Source",
                    "value": "https://github.com/nas5w/svelte-dark"
                },
                {
                    "key": "Microsoft.VisualStudio.Services.Links.GitHub",
                    "value": "https://github.com/nas5w/svelte-dark"
                },
                {
                    "key": "Microsoft.VisualStudio.Code.Engine",
                    "value": "^1.53.0"
                },
                {
                    "key": "Microsoft.VisualStudio.Services.GitHubFlavoredMarkdown",
                    "value": "true"
                },
                {
                    "key": "Microsoft.VisualStudio.Code.ExtensionDependencies",
                    "value": ""
                },
                {
                    "key": "Microsoft.VisualStudio.Code.ExtensionPack",
                    "value": ""
                },
                {
                    "key": "Microsoft.VisualStudio.Code.LocalizedLanguages",
                    "value": ""
                },
                {
                    "key": "Microsoft.VisualStudio.Code.ExtensionKind",
                    "value": "ui,workspace,web"
                }
            ],
            "assetUri": "https://nickscialli.gallerycdn.vsassets.io/extensions/nickscialli/svelte-dark/0.0.4/1613362617047",
            "fallbackAssetUri": "https://nickscialli.gallery.vsassets.io/_apis/public/gallery/publisher/NickScialli/extension/svelte-dark/0.0.4/assetbyname"
        },
        {
            "version": "0.0.3",
            "flags": "validated",
            "lastUpdated": "2021-02-15T04:07:57.69Z",
            "files": [
                {
                    "assetType": "Microsoft.VisualStudio.Code.Manifest",
                    "source": "https://nickscialli.gallerycdn.vsassets.io/extensions/nickscialli/svelte-dark/0.0.3/1613361939089/Microsoft.VisualStudio.Code.Manifest"
                },
                {
                    "assetType": "Microsoft.VisualStudio.Services.Content.Changelog",
                    "source": "https://nickscialli.gallerycdn.vsassets.io/extensions/nickscialli/svelte-dark/0.0.3/1613361939089/Microsoft.VisualStudio.Services.Content.Changelog"
                },
                {
                    "assetType": "Microsoft.VisualStudio.Services.Content.Details",
                    "source": "https://nickscialli.gallerycdn.vsassets.io/extensions/nickscialli/svelte-dark/0.0.3/1613361939089/Microsoft.VisualStudio.Services.Content.Details"
                },
                {
                    "assetType": "Microsoft.VisualStudio.Services.Icons.Default",
                    "source": "https://nickscialli.gallerycdn.vsassets.io/extensions/nickscialli/svelte-dark/0.0.3/1613361939089/Microsoft.VisualStudio.Services.Icons.Default"
                },
                {
                    "assetType": "Microsoft.VisualStudio.Services.Icons.Small",
                    "source": "https://nickscialli.gallerycdn.vsassets.io/extensions/nickscialli/svelte-dark/0.0.3/1613361939089/Microsoft.VisualStudio.Services.Icons.Small"
                },
                {
                    "assetType": "Microsoft.VisualStudio.Services.VsixManifest",
                    "source": "https://nickscialli.gallerycdn.vsassets.io/extensions/nickscialli/svelte-dark/0.0.3/1613361939089/Microsoft.VisualStudio.Services.VsixManifest"
                },
                {
                    "assetType": "Microsoft.VisualStudio.Services.VSIXPackage",
                    "source": "https://nickscialli.gallerycdn.vsassets.io/extensions/nickscialli/svelte-dark/0.0.3/1613361939089/Microsoft.VisualStudio.Services.VSIXPackage"
                }
            ],
            "properties": [
                {
                    "key": "Microsoft.VisualStudio.Services.Links.Getstarted",
                    "value": "https://github.com/nas5w/svelte-dark"
                },
                {
                    "key": "Microsoft.VisualStudio.Services.Links.Source",
                    "value": "https://github.com/nas5w/svelte-dark"
                },
                {
                    "key": "Microsoft.VisualStudio.Services.Links.GitHub",
                    "value": "https://github.com/nas5w/svelte-dark"
                },
                {
                    "key": "Microsoft.VisualStudio.Code.Engine",
                    "value": "^1.53.0"
                },
                {
                    "key": "Microsoft.VisualStudio.Services.GitHubFlavoredMarkdown",
                    "value": "true"
                },
                {
                    "key": "Microsoft.VisualStudio.Code.ExtensionDependencies",
                    "value": ""
                },
                {
                    "key": "Microsoft.VisualStudio.Code.ExtensionPack",
                    "value": ""
                },
                {
                    "key": "Microsoft.VisualStudio.Code.LocalizedLanguages",
                    "value": ""
                },
                {
                    "key": "Microsoft.VisualStudio.Code.ExtensionKind",
                    "value": "ui,workspace,web"
                }
            ],
            "assetUri": "https://nickscialli.gallerycdn.vsassets.io/extensions/nickscialli/svelte-dark/0.0.3/1613361939089",
            "fallbackAssetUri": "https://nickscialli.gallery.vsassets.io/_apis/public/gallery/publisher/NickScialli/extension/svelte-dark/0.0.3/assetbyname"
        },
        {
            "version": "0.0.2",
            "flags": "validated",
            "lastUpdated": "2021-02-15T03:59:49.313Z",
            "files": [
                {
                    "assetType": "Microsoft.VisualStudio.Code.Manifest",
                    "source": "https://nickscialli.gallerycdn.vsassets.io/extensions/nickscialli/svelte-dark/0.0.2/1613361451688/Microsoft.VisualStudio.Code.Manifest"
                },
                {
                    "assetType": "Microsoft.VisualStudio.Services.Content.Changelog",
                    "source": "https://nickscialli.gallerycdn.vsassets.io/extensions/nickscialli/svelte-dark/0.0.2/1613361451688/Microsoft.VisualStudio.Services.Content.Changelog"
                },
                {
                    "assetType": "Microsoft.VisualStudio.Services.Content.Details",
                    "source": "https://nickscialli.gallerycdn.vsassets.io/extensions/nickscialli/svelte-dark/0.0.2/1613361451688/Microsoft.VisualStudio.Services.Content.Details"
                },
                {
                    "assetType": "Microsoft.VisualStudio.Services.VsixManifest",
                    "source": "https://nickscialli.gallerycdn.vsassets.io/extensions/nickscialli/svelte-dark/0.0.2/1613361451688/Microsoft.VisualStudio.Services.VsixManifest"
                },
                {
                    "assetType": "Microsoft.VisualStudio.Services.VSIXPackage",
                    "source": "https://nickscialli.gallerycdn.vsassets.io/extensions/nickscialli/svelte-dark/0.0.2/1613361451688/Microsoft.VisualStudio.Services.VSIXPackage"
                }
            ],
            "properties": [
                {
                    "key": "Microsoft.VisualStudio.Services.Links.Getstarted",
                    "value": "https://github.com/nas5w/svelte-dark"
                },
                {
                    "key": "Microsoft.VisualStudio.Services.Links.Source",
                    "value": "https://github.com/nas5w/svelte-dark"
                },
                {
                    "key": "Microsoft.VisualStudio.Services.Links.GitHub",
                    "value": "https://github.com/nas5w/svelte-dark"
                },
                {
                    "key": "Microsoft.VisualStudio.Code.Engine",
                    "value": "^1.53.0"
                },
                {
                    "key": "Microsoft.VisualStudio.Services.GitHubFlavoredMarkdown",
                    "value": "true"
                },
                {
                    "key": "Microsoft.VisualStudio.Code.ExtensionDependencies",
                    "value": ""
                },
                {
                    "key": "Microsoft.VisualStudio.Code.ExtensionPack",
                    "value": ""
                },
                {
                    "key": "Microsoft.VisualStudio.Code.LocalizedLanguages",
                    "value": ""
                },
                {
                    "key": "Microsoft.VisualStudio.Code.ExtensionKind",
                    "value": "ui,workspace,web"
                }
            ],
            "assetUri": "https://nickscialli.gallerycdn.vsassets.io/extensions/nickscialli/svelte-dark/0.0.2/1613361451688",
            "fallbackAssetUri": "https://nickscialli.gallery.vsassets.io/_apis/public/gallery/publisher/NickScialli/extension/svelte-dark/0.0.2/assetbyname"
        },
        {
            "version": "0.0.1",
            "flags": "validated",
            "lastUpdated": "2021-02-15T03:40:40.823Z",
            "files": [
                {
                    "assetType": "Microsoft.VisualStudio.Code.Manifest",
                    "source": "https://nickscialli.gallerycdn.vsassets.io/extensions/nickscialli/svelte-dark/0.0.1/1613360303358/Microsoft.VisualStudio.Code.Manifest"
                },
                {
                    "assetType": "Microsoft.VisualStudio.Services.Content.Changelog",
                    "source": "https://nickscialli.gallerycdn.vsassets.io/extensions/nickscialli/svelte-dark/0.0.1/1613360303358/Microsoft.VisualStudio.Services.Content.Changelog"
                },
                {
                    "assetType": "Microsoft.VisualStudio.Services.Content.Details",
                    "source": "https://nickscialli.gallerycdn.vsassets.io/extensions/nickscialli/svelte-dark/0.0.1/1613360303358/Microsoft.VisualStudio.Services.Content.Details"
                },
                {
                    "assetType": "Microsoft.VisualStudio.Services.VsixManifest",
                    "source": "https://nickscialli.gallerycdn.vsassets.io/extensions/nickscialli/svelte-dark/0.0.1/1613360303358/Microsoft.VisualStudio.Services.VsixManifest"
                },
                {
                    "assetType": "Microsoft.VisualStudio.Services.VSIXPackage",
                    "source": "https://nickscialli.gallerycdn.vsassets.io/extensions/nickscialli/svelte-dark/0.0.1/1613360303358/Microsoft.VisualStudio.Services.VSIXPackage"
                }
            ],
            "properties": [
                {
                    "key": "Microsoft.VisualStudio.Services.Links.Getstarted",
                    "value": "https://github.com/nas5w/svelte-dark"
                },
                {
                    "key": "Microsoft.VisualStudio.Services.Links.Source",
                    "value": "https://github.com/nas5w/svelte-dark"
                },
                {
                    "key": "Microsoft.VisualStudio.Services.Links.GitHub",
                    "value": "https://github.com/nas5w/svelte-dark"
                },
                {
                    "key": "Microsoft.VisualStudio.Code.Engine",
                    "value": "^1.53.0"
                },
                {
                    "key": "Microsoft.VisualStudio.Services.GitHubFlavoredMarkdown",
                    "value": "true"
                },
                {
                    "key": "Microsoft.VisualStudio.Code.ExtensionDependencies",
                    "value": ""
                },
                {
                    "key": "Microsoft.VisualStudio.Code.ExtensionPack",
                    "value": ""
                },
                {
                    "key": "Microsoft.VisualStudio.Code.LocalizedLanguages",
                    "value": ""
                },
                {
                    "key": "Microsoft.VisualStudio.Code.ExtensionKind",
                    "value": "ui,workspace,web"
                }
            ],
            "assetUri": "https://nickscialli.gallerycdn.vsassets.io/extensions/nickscialli/svelte-dark/0.0.1/1613360303358",
            "fallbackAssetUri": "https://nickscialli.gallery.vsassets.io/_apis/public/gallery/publisher/NickScialli/extension/svelte-dark/0.0.1/assetbyname"
        }
    ],
    "categories": [
        "Themes"
    ],
    "tags": [
        "__web_extension",
        "color-theme",
        "html",
        "javascript",
        "svelte",
        "theme",
        "typescript"
    ],
    "statistics": [
        {
            "statisticName": "install",
            "value": 7937.0
        },
        {
            "statisticName": "averagerating",
            "value": 4.666666507720947
        },
        {
            "statisticName": "ratingcount",
            "value": 3.0
        },
        {
            "statisticName": "trendingdaily",
            "value": 0.0
        },
        {
            "statisticName": "trendingmonthly",
            "value": 2.5828398639284362
        },
        {
            "statisticName": "trendingweekly",
            "value": 0.6425601612700013
        },
        {
            "statisticName": "updateCount",
            "value": 46.0
        },
        {
            "statisticName": "weightedRating",
            "value": 4.464003601250429
        },
        {
            "statisticName": "downloadCount",
            "value": 50.0
        }
    ],
    "installationTargets": [
        {
            "target": "Microsoft.VisualStudio.Code",
            "targetVersion": ""
        }
    ],
    "deploymentType": 0
}