{
    "publisher": {
        "publisherId": "8cd0045f-a620-41dd-a160-4e8eab00e5d1",
        "publisherName": "TheRealToxicDev",
        "displayName": "TheRealToxicDev",
        "flags": "verified",
        "domain": "https://toxicdev.me",
        "isDomainVerified": false
    },
    "extensionId": "956b9278-8280-46a4-870b-2b22833d02e7",
    "extensionName": "toxics-rpc",
    "displayName": "Toxics RPC",
    "flags": "validated, public",
    "lastUpdated": "2023-02-05T22:07:05.99Z",
    "publishedDate": "2021-12-31T10:56:22.003Z",
    "releaseDate": "2021-12-31T10:56:22.003Z",
    "shortDescription": "Customizable Discord Rich Presence for Visual Studio Code",
    "versions": [
        {
            "version": "1.1.4",
            "flags": "validated",
            "lastUpdated": "2023-02-05T22:07:05.99Z",
            "files": [
                {
                    "assetType": "Microsoft.VisualStudio.Code.Manifest",
                    "source": "https://therealtoxicdev.gallerycdn.vsassets.io/extensions/therealtoxicdev/toxics-rpc/1.1.4/1675634658456/Microsoft.VisualStudio.Code.Manifest"
                },
                {
                    "assetType": "Microsoft.VisualStudio.Services.Content.Details",
                    "source": "https://therealtoxicdev.gallerycdn.vsassets.io/extensions/therealtoxicdev/toxics-rpc/1.1.4/1675634658456/Microsoft.VisualStudio.Services.Content.Details"
                },
                {
                    "assetType": "Microsoft.VisualStudio.Services.Content.License",
                    "source": "https://therealtoxicdev.gallerycdn.vsassets.io/extensions/therealtoxicdev/toxics-rpc/1.1.4/1675634658456/Microsoft.VisualStudio.Services.Content.License"
                },
                {
                    "assetType": "Microsoft.VisualStudio.Services.Icons.Default",
                    "source": "https://therealtoxicdev.gallerycdn.vsassets.io/extensions/therealtoxicdev/toxics-rpc/1.1.4/1675634658456/Microsoft.VisualStudio.Services.Icons.Default"
                },
                {
                    "assetType": "Microsoft.VisualStudio.Services.Icons.Small",
                    "source": "https://therealtoxicdev.gallerycdn.vsassets.io/extensions/therealtoxicdev/toxics-rpc/1.1.4/1675634658456/Microsoft.VisualStudio.Services.Icons.Small"
                },
                {
                    "assetType": "Microsoft.VisualStudio.Services.VsixManifest",
                    "source": "https://therealtoxicdev.gallerycdn.vsassets.io/extensions/therealtoxicdev/toxics-rpc/1.1.4/1675634658456/Microsoft.VisualStudio.Services.VsixManifest"
                },
                {
                    "assetType": "Microsoft.VisualStudio.Services.VSIXPackage",
                    "source": "https://therealtoxicdev.gallerycdn.vsassets.io/extensions/therealtoxicdev/toxics-rpc/1.1.4/1675634658456/Microsoft.VisualStudio.Services.VSIXPackage"
                },
                {
                    "assetType": "Microsoft.VisualStudio.Services.VsixSignature",
                    "source": "https://therealtoxicdev.gallerycdn.vsassets.io/extensions/therealtoxicdev/toxics-rpc/1.1.4/1675634658456/Microsoft.VisualStudio.Services.VsixSignature"
                }
            ],
            "properties": [
                {
                    "key": "Microsoft.VisualStudio.Services.Branding.Color",
                    "value": "#5865F2"
                },
                {
                    "key": "Microsoft.VisualStudio.Services.Branding.Theme",
                    "value": "dark"
                },
                {
                    "key": "Microsoft.VisualStudio.Services.Links.Getstarted",
                    "value": "https://github.com/TheRealToxicDev/Toxics-RPC.git"
                },
                {
                    "key": "Microsoft.VisualStudio.Services.Links.Support",
                    "value": "https://github.com/TheRealToxicDev/Toxics-RPC/issues"
                },
                {
                    "key": "Microsoft.VisualStudio.Services.Links.Learn",
                    "value": "https://github.com/TheRealToxicDev/Toxics-RPC#readme"
                },
                {
                    "key": "Microsoft.VisualStudio.Services.Links.Source",
                    "value": "https://github.com/TheRealToxicDev/Toxics-RPC.git"
                },
                {
                    "key": "Microsoft.VisualStudio.Services.Links.GitHub",
                    "value": "https://github.com/TheRealToxicDev/Toxics-RPC.git"
                },
                {
                    "key": "Microsoft.VisualStudio.Code.Engine",
                    "value": "^1.59.0"
                },
                {
                    "key": "Microsoft.VisualStudio.Services.GitHubFlavoredMarkdown",
                    "value": "true"
                },
                {
                    "key": "Microsoft.VisualStudio.Code.ExtensionDependencies",
                    "value": ""
                },
                {
                    "key": "Microsoft.VisualStudio.Code.ExtensionPack",
                    "value": ""
                },
                {
                    "key": "Microsoft.VisualStudio.Code.LocalizedLanguages",
                    "value": ""
                },
                {
                    "key": "Microsoft.VisualStudio.Code.ExtensionKind",
                    "value": "ui,workspace"
                }
            ],
            "assetUri": "https://therealtoxicdev.gallerycdn.vsassets.io/extensions/therealtoxicdev/toxics-rpc/1.1.4/1675634658456",
            "fallbackAssetUri": "https://therealtoxicdev.gallery.vsassets.io/_apis/public/gallery/publisher/TheRealToxicDev/extension/toxics-rpc/1.1.4/assetbyname"
        },
        {
            "version": "1.1.3",
            "flags": "validated",
            "lastUpdated": "2023-01-02T23:38:03.61Z",
            "files": [
                {
                    "assetType": "Microsoft.VisualStudio.Code.Manifest",
                    "source": "https://therealtoxicdev.gallerycdn.vsassets.io/extensions/therealtoxicdev/toxics-rpc/1.1.3/1672702522283/Microsoft.VisualStudio.Code.Manifest"
                },
                {
                    "assetType": "Microsoft.VisualStudio.Services.Content.Details",
                    "source": "https://therealtoxicdev.gallerycdn.vsassets.io/extensions/therealtoxicdev/toxics-rpc/1.1.3/1672702522283/Microsoft.VisualStudio.Services.Content.Details"
                },
                {
                    "assetType": "Microsoft.VisualStudio.Services.Content.License",
                    "source": "https://therealtoxicdev.gallerycdn.vsassets.io/extensions/therealtoxicdev/toxics-rpc/1.1.3/1672702522283/Microsoft.VisualStudio.Services.Content.License"
                },
                {
                    "assetType": "Microsoft.VisualStudio.Services.Icons.Default",
                    "source": "https://therealtoxicdev.gallerycdn.vsassets.io/extensions/therealtoxicdev/toxics-rpc/1.1.3/1672702522283/Microsoft.VisualStudio.Services.Icons.Default"
                },
                {
                    "assetType": "Microsoft.VisualStudio.Services.Icons.Small",
                    "source": "https://therealtoxicdev.gallerycdn.vsassets.io/extensions/therealtoxicdev/toxics-rpc/1.1.3/1672702522283/Microsoft.VisualStudio.Services.Icons.Small"
                },
                {
                    "assetType": "Microsoft.VisualStudio.Services.VsixManifest",
                    "source": "https://therealtoxicdev.gallerycdn.vsassets.io/extensions/therealtoxicdev/toxics-rpc/1.1.3/1672702522283/Microsoft.VisualStudio.Services.VsixManifest"
                },
                {
                    "assetType": "Microsoft.VisualStudio.Services.VSIXPackage",
                    "source": "https://therealtoxicdev.gallerycdn.vsassets.io/extensions/therealtoxicdev/toxics-rpc/1.1.3/1672702522283/Microsoft.VisualStudio.Services.VSIXPackage"
                },
                {
                    "assetType": "Microsoft.VisualStudio.Services.VsixSignature",
                    "source": "https://therealtoxicdev.gallerycdn.vsassets.io/extensions/therealtoxicdev/toxics-rpc/1.1.3/1672702522283/Microsoft.VisualStudio.Services.VsixSignature"
                }
            ],
            "properties": [
                {
                    "key": "Microsoft.VisualStudio.Services.Branding.Color",
                    "value": "#5865F2"
                },
                {
                    "key": "Microsoft.VisualStudio.Services.Branding.Theme",
                    "value": "dark"
                },
                {
                    "key": "Microsoft.VisualStudio.Services.Links.Getstarted",
                    "value": "https://github.com/TheRealToxicDev/Toxics-RPC.git"
                },
                {
                    "key": "Microsoft.VisualStudio.Services.Links.Support",
                    "value": "https://github.com/TheRealToxicDev/Toxics-RPC/issues"
                },
                {
                    "key": "Microsoft.VisualStudio.Services.Links.Learn",
                    "value": "https://github.com/TheRealToxicDev/Toxics-RPC#readme"
                },
                {
                    "key": "Microsoft.VisualStudio.Services.Links.Source",
                    "value": "https://github.com/TheRealToxicDev/Toxics-RPC.git"
                },
                {
                    "key": "Microsoft.VisualStudio.Services.Links.GitHub",
                    "value": "https://github.com/TheRealToxicDev/Toxics-RPC.git"
                },
                {
                    "key": "Microsoft.VisualStudio.Code.Engine",
                    "value": "^1.59.0"
                },
                {
                    "key": "Microsoft.VisualStudio.Services.GitHubFlavoredMarkdown",
                    "value": "true"
                },
                {
                    "key": "Microsoft.VisualStudio.Code.ExtensionDependencies",
                    "value": ""
                },
                {
                    "key": "Microsoft.VisualStudio.Code.ExtensionPack",
                    "value": ""
                },
                {
                    "key": "Microsoft.VisualStudio.Code.LocalizedLanguages",
                    "value": ""
                },
                {
                    "key": "Microsoft.VisualStudio.Code.ExtensionKind",
                    "value": "ui,workspace"
                }
            ],
            "assetUri": "https://therealtoxicdev.gallerycdn.vsassets.io/extensions/therealtoxicdev/toxics-rpc/1.1.3/1672702522283",
            "fallbackAssetUri": "https://therealtoxicdev.gallery.vsassets.io/_apis/public/gallery/publisher/TheRealToxicDev/extension/toxics-rpc/1.1.3/assetbyname"
        },
        {
            "version": "1.1.2",
            "flags": "validated",
            "lastUpdated": "2022-01-01T01:27:41.71Z",
            "files": [
                {
                    "assetType": "Microsoft.VisualStudio.Code.Manifest",
                    "source": "https://therealtoxicdev.gallerycdn.vsassets.io/extensions/therealtoxicdev/toxics-rpc/1.1.2/1641000321155/Microsoft.VisualStudio.Code.Manifest"
                },
                {
                    "assetType": "Microsoft.VisualStudio.Services.Content.Details",
                    "source": "https://therealtoxicdev.gallerycdn.vsassets.io/extensions/therealtoxicdev/toxics-rpc/1.1.2/1641000321155/Microsoft.VisualStudio.Services.Content.Details"
                },
                {
                    "assetType": "Microsoft.VisualStudio.Services.Content.License",
                    "source": "https://therealtoxicdev.gallerycdn.vsassets.io/extensions/therealtoxicdev/toxics-rpc/1.1.2/1641000321155/Microsoft.VisualStudio.Services.Content.License"
                },
                {
                    "assetType": "Microsoft.VisualStudio.Services.Icons.Default",
                    "source": "https://therealtoxicdev.gallerycdn.vsassets.io/extensions/therealtoxicdev/toxics-rpc/1.1.2/1641000321155/Microsoft.VisualStudio.Services.Icons.Default"
                },
                {
                    "assetType": "Microsoft.VisualStudio.Services.Icons.Small",
                    "source": "https://therealtoxicdev.gallerycdn.vsassets.io/extensions/therealtoxicdev/toxics-rpc/1.1.2/1641000321155/Microsoft.VisualStudio.Services.Icons.Small"
                },
                {
                    "assetType": "Microsoft.VisualStudio.Services.VsixManifest",
                    "source": "https://therealtoxicdev.gallerycdn.vsassets.io/extensions/therealtoxicdev/toxics-rpc/1.1.2/1641000321155/Microsoft.VisualStudio.Services.VsixManifest"
                },
                {
                    "assetType": "Microsoft.VisualStudio.Services.VSIXPackage",
                    "source": "https://therealtoxicdev.gallerycdn.vsassets.io/extensions/therealtoxicdev/toxics-rpc/1.1.2/1641000321155/Microsoft.VisualStudio.Services.VSIXPackage"
                }
            ],
            "properties": [
                {
                    "key": "Microsoft.VisualStudio.Services.Branding.Color",
                    "value": "#5865F2"
                },
                {
                    "key": "Microsoft.VisualStudio.Services.Branding.Theme",
                    "value": "dark"
                },
                {
                    "key": "Microsoft.VisualStudio.Services.Links.Getstarted",
                    "value": "https://github.com/TheRealToxicDev/Toxics-RPC.git"
                },
                {
                    "key": "Microsoft.VisualStudio.Services.Links.Support",
                    "value": "https://github.com/TheRealToxicDev/Toxics-RPC/issues"
                },
                {
                    "key": "Microsoft.VisualStudio.Services.Links.Learn",
                    "value": "https://github.com/TheRealToxicDev/Toxics-RPC#readme"
                },
                {
                    "key": "Microsoft.VisualStudio.Services.Links.Source",
                    "value": "https://github.com/TheRealToxicDev/Toxics-RPC.git"
                },
                {
                    "key": "Microsoft.VisualStudio.Services.Links.GitHub",
                    "value": "https://github.com/TheRealToxicDev/Toxics-RPC.git"
                },
                {
                    "key": "Microsoft.VisualStudio.Code.Engine",
                    "value": "^1.59.0"
                },
                {
                    "key": "Microsoft.VisualStudio.Services.GitHubFlavoredMarkdown",
                    "value": "true"
                },
                {
                    "key": "Microsoft.VisualStudio.Code.ExtensionDependencies",
                    "value": ""
                },
                {
                    "key": "Microsoft.VisualStudio.Code.ExtensionPack",
                    "value": ""
                },
                {
                    "key": "Microsoft.VisualStudio.Code.LocalizedLanguages",
                    "value": ""
                },
                {
                    "key": "Microsoft.VisualStudio.Code.ExtensionKind",
                    "value": "ui,workspace"
                }
            ],
            "assetUri": "https://therealtoxicdev.gallerycdn.vsassets.io/extensions/therealtoxicdev/toxics-rpc/1.1.2/1641000321155",
            "fallbackAssetUri": "https://therealtoxicdev.gallery.vsassets.io/_apis/public/gallery/publisher/TheRealToxicDev/extension/toxics-rpc/1.1.2/assetbyname"
        },
        {
            "version": "1.1.1",
            "flags": "validated",
            "lastUpdated": "2022-01-01T00:45:09.03Z",
            "files": [
                {
                    "assetType": "Microsoft.VisualStudio.Code.Manifest",
                    "source": "https://therealtoxicdev.gallerycdn.vsassets.io/extensions/therealtoxicdev/toxics-rpc/1.1.1/1640997769987/Microsoft.VisualStudio.Code.Manifest"
                },
                {
                    "assetType": "Microsoft.VisualStudio.Services.Content.Details",
                    "source": "https://therealtoxicdev.gallerycdn.vsassets.io/extensions/therealtoxicdev/toxics-rpc/1.1.1/1640997769987/Microsoft.VisualStudio.Services.Content.Details"
                },
                {
                    "assetType": "Microsoft.VisualStudio.Services.Content.License",
                    "source": "https://therealtoxicdev.gallerycdn.vsassets.io/extensions/therealtoxicdev/toxics-rpc/1.1.1/1640997769987/Microsoft.VisualStudio.Services.Content.License"
                },
                {
                    "assetType": "Microsoft.VisualStudio.Services.Icons.Default",
                    "source": "https://therealtoxicdev.gallerycdn.vsassets.io/extensions/therealtoxicdev/toxics-rpc/1.1.1/1640997769987/Microsoft.VisualStudio.Services.Icons.Default"
                },
                {
                    "assetType": "Microsoft.VisualStudio.Services.Icons.Small",
                    "source": "https://therealtoxicdev.gallerycdn.vsassets.io/extensions/therealtoxicdev/toxics-rpc/1.1.1/1640997769987/Microsoft.VisualStudio.Services.Icons.Small"
                },
                {
                    "assetType": "Microsoft.VisualStudio.Services.VsixManifest",
                    "source": "https://therealtoxicdev.gallerycdn.vsassets.io/extensions/therealtoxicdev/toxics-rpc/1.1.1/1640997769987/Microsoft.VisualStudio.Services.VsixManifest"
                },
                {
                    "assetType": "Microsoft.VisualStudio.Services.VSIXPackage",
                    "source": "https://therealtoxicdev.gallerycdn.vsassets.io/extensions/therealtoxicdev/toxics-rpc/1.1.1/1640997769987/Microsoft.VisualStudio.Services.VSIXPackage"
                }
            ],
            "properties": [
                {
                    "key": "Microsoft.VisualStudio.Services.Branding.Color",
                    "value": "#5865F2"
                },
                {
                    "key": "Microsoft.VisualStudio.Services.Branding.Theme",
                    "value": "dark"
                },
                {
                    "key": "Microsoft.VisualStudio.Services.Links.Getstarted",
                    "value": "https://github.com/TheRealToxicDev/Toxics-RPC.git"
                },
                {
                    "key": "Microsoft.VisualStudio.Services.Links.Support",
                    "value": "https://github.com/TheRealToxicDev/Toxics-RPC/issues"
                },
                {
                    "key": "Microsoft.VisualStudio.Services.Links.Learn",
                    "value": "https://github.com/TheRealToxicDev/Toxics-RPC#readme"
                },
                {
                    "key": "Microsoft.VisualStudio.Services.Links.Source",
                    "value": "https://github.com/TheRealToxicDev/Toxics-RPC.git"
                },
                {
                    "key": "Microsoft.VisualStudio.Services.Links.GitHub",
                    "value": "https://github.com/TheRealToxicDev/Toxics-RPC.git"
                },
                {
                    "key": "Microsoft.VisualStudio.Code.Engine",
                    "value": "^1.59.0"
                },
                {
                    "key": "Microsoft.VisualStudio.Services.GitHubFlavoredMarkdown",
                    "value": "true"
                },
                {
                    "key": "Microsoft.VisualStudio.Code.ExtensionDependencies",
                    "value": ""
                },
                {
                    "key": "Microsoft.VisualStudio.Code.ExtensionPack",
                    "value": ""
                },
                {
                    "key": "Microsoft.VisualStudio.Code.LocalizedLanguages",
                    "value": ""
                },
                {
                    "key": "Microsoft.VisualStudio.Code.ExtensionKind",
                    "value": "ui,workspace"
                }
            ],
            "assetUri": "https://therealtoxicdev.gallerycdn.vsassets.io/extensions/therealtoxicdev/toxics-rpc/1.1.1/1640997769987",
            "fallbackAssetUri": "https://therealtoxicdev.gallery.vsassets.io/_apis/public/gallery/publisher/TheRealToxicDev/extension/toxics-rpc/1.1.1/assetbyname"
        },
        {
            "version": "1.1.0",
            "flags": "validated",
            "lastUpdated": "2021-12-31T21:14:29.507Z",
            "files": [
                {
                    "assetType": "Microsoft.VisualStudio.Code.Manifest",
                    "source": "https://therealtoxicdev.gallerycdn.vsassets.io/extensions/therealtoxicdev/toxics-rpc/1.1.0/1640985131493/Microsoft.VisualStudio.Code.Manifest"
                },
                {
                    "assetType": "Microsoft.VisualStudio.Services.Content.Details",
                    "source": "https://therealtoxicdev.gallerycdn.vsassets.io/extensions/therealtoxicdev/toxics-rpc/1.1.0/1640985131493/Microsoft.VisualStudio.Services.Content.Details"
                },
                {
                    "assetType": "Microsoft.VisualStudio.Services.Content.License",
                    "source": "https://therealtoxicdev.gallerycdn.vsassets.io/extensions/therealtoxicdev/toxics-rpc/1.1.0/1640985131493/Microsoft.VisualStudio.Services.Content.License"
                },
                {
                    "assetType": "Microsoft.VisualStudio.Services.Icons.Default",
                    "source": "https://therealtoxicdev.gallerycdn.vsassets.io/extensions/therealtoxicdev/toxics-rpc/1.1.0/1640985131493/Microsoft.VisualStudio.Services.Icons.Default"
                },
                {
                    "assetType": "Microsoft.VisualStudio.Services.Icons.Small",
                    "source": "https://therealtoxicdev.gallerycdn.vsassets.io/extensions/therealtoxicdev/toxics-rpc/1.1.0/1640985131493/Microsoft.VisualStudio.Services.Icons.Small"
                },
                {
                    "assetType": "Microsoft.VisualStudio.Services.VsixManifest",
                    "source": "https://therealtoxicdev.gallerycdn.vsassets.io/extensions/therealtoxicdev/toxics-rpc/1.1.0/1640985131493/Microsoft.VisualStudio.Services.VsixManifest"
                },
                {
                    "assetType": "Microsoft.VisualStudio.Services.VSIXPackage",
                    "source": "https://therealtoxicdev.gallerycdn.vsassets.io/extensions/therealtoxicdev/toxics-rpc/1.1.0/1640985131493/Microsoft.VisualStudio.Services.VSIXPackage"
                }
            ],
            "properties": [
                {
                    "key": "Microsoft.VisualStudio.Services.Branding.Color",
                    "value": "#5865F2"
                },
                {
                    "key": "Microsoft.VisualStudio.Services.Branding.Theme",
                    "value": "dark"
                },
                {
                    "key": "Microsoft.VisualStudio.Services.Links.Getstarted",
                    "value": "https://github.com/TheRealToxicDev/Toxics-RPC.git"
                },
                {
                    "key": "Microsoft.VisualStudio.Services.Links.Support",
                    "value": "https://github.com/TheRealToxicDev/Toxics-RPC/issues"
                },
                {
                    "key": "Microsoft.VisualStudio.Services.Links.Learn",
                    "value": "https://github.com/TheRealToxicDev/Toxics-RPC#readme"
                },
                {
                    "key": "Microsoft.VisualStudio.Services.Links.Source",
                    "value": "https://github.com/TheRealToxicDev/Toxics-RPC.git"
                },
                {
                    "key": "Microsoft.VisualStudio.Services.Links.GitHub",
                    "value": "https://github.com/TheRealToxicDev/Toxics-RPC.git"
                },
                {
                    "key": "Microsoft.VisualStudio.Code.Engine",
                    "value": "^1.59.0"
                },
                {
                    "key": "Microsoft.VisualStudio.Services.GitHubFlavoredMarkdown",
                    "value": "true"
                },
                {
                    "key": "Microsoft.VisualStudio.Code.ExtensionDependencies",
                    "value": ""
                },
                {
                    "key": "Microsoft.VisualStudio.Code.ExtensionPack",
                    "value": ""
                },
                {
                    "key": "Microsoft.VisualStudio.Code.LocalizedLanguages",
                    "value": ""
                },
                {
                    "key": "Microsoft.VisualStudio.Code.ExtensionKind",
                    "value": "ui,workspace"
                }
            ],
            "assetUri": "https://therealtoxicdev.gallerycdn.vsassets.io/extensions/therealtoxicdev/toxics-rpc/1.1.0/1640985131493",
            "fallbackAssetUri": "https://therealtoxicdev.gallery.vsassets.io/_apis/public/gallery/publisher/TheRealToxicDev/extension/toxics-rpc/1.1.0/assetbyname"
        },
        {
            "version": "1.0.9",
            "flags": "validated",
            "lastUpdated": "2021-12-31T21:12:01.77Z",
            "files": [
                {
                    "assetType": "Microsoft.VisualStudio.Code.Manifest",
                    "source": "https://therealtoxicdev.gallerycdn.vsassets.io/extensions/therealtoxicdev/toxics-rpc/1.0.9/1640984982153/Microsoft.VisualStudio.Code.Manifest"
                },
                {
                    "assetType": "Microsoft.VisualStudio.Services.Content.Details",
                    "source": "https://therealtoxicdev.gallerycdn.vsassets.io/extensions/therealtoxicdev/toxics-rpc/1.0.9/1640984982153/Microsoft.VisualStudio.Services.Content.Details"
                },
                {
                    "assetType": "Microsoft.VisualStudio.Services.Content.License",
                    "source": "https://therealtoxicdev.gallerycdn.vsassets.io/extensions/therealtoxicdev/toxics-rpc/1.0.9/1640984982153/Microsoft.VisualStudio.Services.Content.License"
                },
                {
                    "assetType": "Microsoft.VisualStudio.Services.Icons.Default",
                    "source": "https://therealtoxicdev.gallerycdn.vsassets.io/extensions/therealtoxicdev/toxics-rpc/1.0.9/1640984982153/Microsoft.VisualStudio.Services.Icons.Default"
                },
                {
                    "assetType": "Microsoft.VisualStudio.Services.Icons.Small",
                    "source": "https://therealtoxicdev.gallerycdn.vsassets.io/extensions/therealtoxicdev/toxics-rpc/1.0.9/1640984982153/Microsoft.VisualStudio.Services.Icons.Small"
                },
                {
                    "assetType": "Microsoft.VisualStudio.Services.VsixManifest",
                    "source": "https://therealtoxicdev.gallerycdn.vsassets.io/extensions/therealtoxicdev/toxics-rpc/1.0.9/1640984982153/Microsoft.VisualStudio.Services.VsixManifest"
                },
                {
                    "assetType": "Microsoft.VisualStudio.Services.VSIXPackage",
                    "source": "https://therealtoxicdev.gallerycdn.vsassets.io/extensions/therealtoxicdev/toxics-rpc/1.0.9/1640984982153/Microsoft.VisualStudio.Services.VSIXPackage"
                }
            ],
            "properties": [
                {
                    "key": "Microsoft.VisualStudio.Services.Branding.Color",
                    "value": "#5865F2"
                },
                {
                    "key": "Microsoft.VisualStudio.Services.Branding.Theme",
                    "value": "dark"
                },
                {
                    "key": "Microsoft.VisualStudio.Services.Links.Getstarted",
                    "value": "https://github.com/TheRealToxicDev/Toxics-RPC.git"
                },
                {
                    "key": "Microsoft.VisualStudio.Services.Links.Support",
                    "value": "https://github.com/TheRealToxicDev/Toxics-RPC/issues"
                },
                {
                    "key": "Microsoft.VisualStudio.Services.Links.Learn",
                    "value": "https://github.com/TheRealToxicDev/Toxics-RPC#readme"
                },
                {
                    "key": "Microsoft.VisualStudio.Services.Links.Source",
                    "value": "https://github.com/TheRealToxicDev/Toxics-RPC.git"
                },
                {
                    "key": "Microsoft.VisualStudio.Services.Links.GitHub",
                    "value": "https://github.com/TheRealToxicDev/Toxics-RPC.git"
                },
                {
                    "key": "Microsoft.VisualStudio.Code.Engine",
                    "value": "^1.59.0"
                },
                {
                    "key": "Microsoft.VisualStudio.Services.GitHubFlavoredMarkdown",
                    "value": "true"
                },
                {
                    "key": "Microsoft.VisualStudio.Code.ExtensionDependencies",
                    "value": ""
                },
                {
                    "key": "Microsoft.VisualStudio.Code.ExtensionPack",
                    "value": ""
                },
                {
                    "key": "Microsoft.VisualStudio.Code.LocalizedLanguages",
                    "value": ""
                },
                {
                    "key": "Microsoft.VisualStudio.Code.ExtensionKind",
                    "value": "ui,workspace"
                }
            ],
            "assetUri": "https://therealtoxicdev.gallerycdn.vsassets.io/extensions/therealtoxicdev/toxics-rpc/1.0.9/1640984982153",
            "fallbackAssetUri": "https://therealtoxicdev.gallery.vsassets.io/_apis/public/gallery/publisher/TheRealToxicDev/extension/toxics-rpc/1.0.9/assetbyname"
        },
        {
            "version": "1.0.8",
            "flags": "validated",
            "lastUpdated": "2021-12-31T20:59:49.047Z",
            "files": [
                {
                    "assetType": "Microsoft.VisualStudio.Code.Manifest",
                    "source": "https://therealtoxicdev.gallerycdn.vsassets.io/extensions/therealtoxicdev/toxics-rpc/1.0.8/1640984249898/Microsoft.VisualStudio.Code.Manifest"
                },
                {
                    "assetType": "Microsoft.VisualStudio.Services.Content.Details",
                    "source": "https://therealtoxicdev.gallerycdn.vsassets.io/extensions/therealtoxicdev/toxics-rpc/1.0.8/1640984249898/Microsoft.VisualStudio.Services.Content.Details"
                },
                {
                    "assetType": "Microsoft.VisualStudio.Services.Content.License",
                    "source": "https://therealtoxicdev.gallerycdn.vsassets.io/extensions/therealtoxicdev/toxics-rpc/1.0.8/1640984249898/Microsoft.VisualStudio.Services.Content.License"
                },
                {
                    "assetType": "Microsoft.VisualStudio.Services.Icons.Default",
                    "source": "https://therealtoxicdev.gallerycdn.vsassets.io/extensions/therealtoxicdev/toxics-rpc/1.0.8/1640984249898/Microsoft.VisualStudio.Services.Icons.Default"
                },
                {
                    "assetType": "Microsoft.VisualStudio.Services.Icons.Small",
                    "source": "https://therealtoxicdev.gallerycdn.vsassets.io/extensions/therealtoxicdev/toxics-rpc/1.0.8/1640984249898/Microsoft.VisualStudio.Services.Icons.Small"
                },
                {
                    "assetType": "Microsoft.VisualStudio.Services.VsixManifest",
                    "source": "https://therealtoxicdev.gallerycdn.vsassets.io/extensions/therealtoxicdev/toxics-rpc/1.0.8/1640984249898/Microsoft.VisualStudio.Services.VsixManifest"
                },
                {
                    "assetType": "Microsoft.VisualStudio.Services.VSIXPackage",
                    "source": "https://therealtoxicdev.gallerycdn.vsassets.io/extensions/therealtoxicdev/toxics-rpc/1.0.8/1640984249898/Microsoft.VisualStudio.Services.VSIXPackage"
                }
            ],
            "properties": [
                {
                    "key": "Microsoft.VisualStudio.Services.Branding.Color",
                    "value": "#5865F2"
                },
                {
                    "key": "Microsoft.VisualStudio.Services.Branding.Theme",
                    "value": "dark"
                },
                {
                    "key": "Microsoft.VisualStudio.Services.Links.Getstarted",
                    "value": "https://github.com/TheRealToxicDev/Toxics-RPC.git"
                },
                {
                    "key": "Microsoft.VisualStudio.Services.Links.Support",
                    "value": "https://github.com/TheRealToxicDev/Toxics-RPC/issues"
                },
                {
                    "key": "Microsoft.VisualStudio.Services.Links.Learn",
                    "value": "https://github.com/TheRealToxicDev/Toxics-RPC#readme"
                },
                {
                    "key": "Microsoft.VisualStudio.Services.Links.Source",
                    "value": "https://github.com/TheRealToxicDev/Toxics-RPC.git"
                },
                {
                    "key": "Microsoft.VisualStudio.Services.Links.GitHub",
                    "value": "https://github.com/TheRealToxicDev/Toxics-RPC.git"
                },
                {
                    "key": "Microsoft.VisualStudio.Code.Engine",
                    "value": "^1.59.0"
                },
                {
                    "key": "Microsoft.VisualStudio.Services.GitHubFlavoredMarkdown",
                    "value": "true"
                },
                {
                    "key": "Microsoft.VisualStudio.Code.ExtensionDependencies",
                    "value": ""
                },
                {
                    "key": "Microsoft.VisualStudio.Code.ExtensionPack",
                    "value": ""
                },
                {
                    "key": "Microsoft.VisualStudio.Code.LocalizedLanguages",
                    "value": ""
                },
                {
                    "key": "Microsoft.VisualStudio.Code.ExtensionKind",
                    "value": "ui,workspace"
                }
            ],
            "assetUri": "https://therealtoxicdev.gallerycdn.vsassets.io/extensions/therealtoxicdev/toxics-rpc/1.0.8/1640984249898",
            "fallbackAssetUri": "https://therealtoxicdev.gallery.vsassets.io/_apis/public/gallery/publisher/TheRealToxicDev/extension/toxics-rpc/1.0.8/assetbyname"
        },
        {
            "version": "1.0.7",
            "flags": "validated",
            "lastUpdated": "2021-12-31T20:51:25.32Z",
            "files": [
                {
                    "assetType": "Microsoft.VisualStudio.Code.Manifest",
                    "source": "https://therealtoxicdev.gallerycdn.vsassets.io/extensions/therealtoxicdev/toxics-rpc/1.0.7/1640983745916/Microsoft.VisualStudio.Code.Manifest"
                },
                {
                    "assetType": "Microsoft.VisualStudio.Services.Content.Details",
                    "source": "https://therealtoxicdev.gallerycdn.vsassets.io/extensions/therealtoxicdev/toxics-rpc/1.0.7/1640983745916/Microsoft.VisualStudio.Services.Content.Details"
                },
                {
                    "assetType": "Microsoft.VisualStudio.Services.Content.License",
                    "source": "https://therealtoxicdev.gallerycdn.vsassets.io/extensions/therealtoxicdev/toxics-rpc/1.0.7/1640983745916/Microsoft.VisualStudio.Services.Content.License"
                },
                {
                    "assetType": "Microsoft.VisualStudio.Services.Icons.Default",
                    "source": "https://therealtoxicdev.gallerycdn.vsassets.io/extensions/therealtoxicdev/toxics-rpc/1.0.7/1640983745916/Microsoft.VisualStudio.Services.Icons.Default"
                },
                {
                    "assetType": "Microsoft.VisualStudio.Services.Icons.Small",
                    "source": "https://therealtoxicdev.gallerycdn.vsassets.io/extensions/therealtoxicdev/toxics-rpc/1.0.7/1640983745916/Microsoft.VisualStudio.Services.Icons.Small"
                },
                {
                    "assetType": "Microsoft.VisualStudio.Services.VsixManifest",
                    "source": "https://therealtoxicdev.gallerycdn.vsassets.io/extensions/therealtoxicdev/toxics-rpc/1.0.7/1640983745916/Microsoft.VisualStudio.Services.VsixManifest"
                },
                {
                    "assetType": "Microsoft.VisualStudio.Services.VSIXPackage",
                    "source": "https://therealtoxicdev.gallerycdn.vsassets.io/extensions/therealtoxicdev/toxics-rpc/1.0.7/1640983745916/Microsoft.VisualStudio.Services.VSIXPackage"
                }
            ],
            "properties": [
                {
                    "key": "Microsoft.VisualStudio.Services.Branding.Color",
                    "value": "#5865F2"
                },
                {
                    "key": "Microsoft.VisualStudio.Services.Branding.Theme",
                    "value": "dark"
                },
                {
                    "key": "Microsoft.VisualStudio.Services.Links.Getstarted",
                    "value": "https://github.com/TheRealToxicDev/Toxics-RPC.git"
                },
                {
                    "key": "Microsoft.VisualStudio.Services.Links.Support",
                    "value": "https://github.com/TheRealToxicDev/Toxics-RPC/issues"
                },
                {
                    "key": "Microsoft.VisualStudio.Services.Links.Learn",
                    "value": "https://github.com/TheRealToxicDev/Toxics-RPC#readme"
                },
                {
                    "key": "Microsoft.VisualStudio.Services.Links.Source",
                    "value": "https://github.com/TheRealToxicDev/Toxics-RPC.git"
                },
                {
                    "key": "Microsoft.VisualStudio.Services.Links.GitHub",
                    "value": "https://github.com/TheRealToxicDev/Toxics-RPC.git"
                },
                {
                    "key": "Microsoft.VisualStudio.Code.Engine",
                    "value": "^1.59.0"
                },
                {
                    "key": "Microsoft.VisualStudio.Services.GitHubFlavoredMarkdown",
                    "value": "true"
                },
                {
                    "key": "Microsoft.VisualStudio.Code.ExtensionDependencies",
                    "value": ""
                },
                {
                    "key": "Microsoft.VisualStudio.Code.ExtensionPack",
                    "value": ""
                },
                {
                    "key": "Microsoft.VisualStudio.Code.LocalizedLanguages",
                    "value": ""
                },
                {
                    "key": "Microsoft.VisualStudio.Code.ExtensionKind",
                    "value": "ui,workspace"
                }
            ],
            "assetUri": "https://therealtoxicdev.gallerycdn.vsassets.io/extensions/therealtoxicdev/toxics-rpc/1.0.7/1640983745916",
            "fallbackAssetUri": "https://therealtoxicdev.gallery.vsassets.io/_apis/public/gallery/publisher/TheRealToxicDev/extension/toxics-rpc/1.0.7/assetbyname"
        },
        {
            "version": "1.0.6",
            "flags": "validated",
            "lastUpdated": "2021-12-31T20:44:46.163Z",
            "files": [
                {
                    "assetType": "Microsoft.VisualStudio.Code.Manifest",
                    "source": "https://therealtoxicdev.gallerycdn.vsassets.io/extensions/therealtoxicdev/toxics-rpc/1.0.6/1640983344223/Microsoft.VisualStudio.Code.Manifest"
                },
                {
                    "assetType": "Microsoft.VisualStudio.Services.Content.Details",
                    "source": "https://therealtoxicdev.gallerycdn.vsassets.io/extensions/therealtoxicdev/toxics-rpc/1.0.6/1640983344223/Microsoft.VisualStudio.Services.Content.Details"
                },
                {
                    "assetType": "Microsoft.VisualStudio.Services.Content.License",
                    "source": "https://therealtoxicdev.gallerycdn.vsassets.io/extensions/therealtoxicdev/toxics-rpc/1.0.6/1640983344223/Microsoft.VisualStudio.Services.Content.License"
                },
                {
                    "assetType": "Microsoft.VisualStudio.Services.Icons.Default",
                    "source": "https://therealtoxicdev.gallerycdn.vsassets.io/extensions/therealtoxicdev/toxics-rpc/1.0.6/1640983344223/Microsoft.VisualStudio.Services.Icons.Default"
                },
                {
                    "assetType": "Microsoft.VisualStudio.Services.Icons.Small",
                    "source": "https://therealtoxicdev.gallerycdn.vsassets.io/extensions/therealtoxicdev/toxics-rpc/1.0.6/1640983344223/Microsoft.VisualStudio.Services.Icons.Small"
                },
                {
                    "assetType": "Microsoft.VisualStudio.Services.VsixManifest",
                    "source": "https://therealtoxicdev.gallerycdn.vsassets.io/extensions/therealtoxicdev/toxics-rpc/1.0.6/1640983344223/Microsoft.VisualStudio.Services.VsixManifest"
                },
                {
                    "assetType": "Microsoft.VisualStudio.Services.VSIXPackage",
                    "source": "https://therealtoxicdev.gallerycdn.vsassets.io/extensions/therealtoxicdev/toxics-rpc/1.0.6/1640983344223/Microsoft.VisualStudio.Services.VSIXPackage"
                }
            ],
            "properties": [
                {
                    "key": "Microsoft.VisualStudio.Services.Branding.Color",
                    "value": "#5865F2"
                },
                {
                    "key": "Microsoft.VisualStudio.Services.Branding.Theme",
                    "value": "dark"
                },
                {
                    "key": "Microsoft.VisualStudio.Services.Links.Getstarted",
                    "value": "https://github.com/TheRealToxicDev/Toxics-RPC.git"
                },
                {
                    "key": "Microsoft.VisualStudio.Services.Links.Support",
                    "value": "https://github.com/TheRealToxicDev/Toxics-RPC/issues"
                },
                {
                    "key": "Microsoft.VisualStudio.Services.Links.Learn",
                    "value": "https://github.com/TheRealToxicDev/Toxics-RPC#readme"
                },
                {
                    "key": "Microsoft.VisualStudio.Services.Links.Source",
                    "value": "https://github.com/TheRealToxicDev/Toxics-RPC.git"
                },
                {
                    "key": "Microsoft.VisualStudio.Services.Links.GitHub",
                    "value": "https://github.com/TheRealToxicDev/Toxics-RPC.git"
                },
                {
                    "key": "Microsoft.VisualStudio.Code.Engine",
                    "value": "^1.59.0"
                },
                {
                    "key": "Microsoft.VisualStudio.Services.GitHubFlavoredMarkdown",
                    "value": "true"
                },
                {
                    "key": "Microsoft.VisualStudio.Code.ExtensionDependencies",
                    "value": ""
                },
                {
                    "key": "Microsoft.VisualStudio.Code.ExtensionPack",
                    "value": ""
                },
                {
                    "key": "Microsoft.VisualStudio.Code.LocalizedLanguages",
                    "value": ""
                },
                {
                    "key": "Microsoft.VisualStudio.Code.ExtensionKind",
                    "value": "ui,workspace"
                }
            ],
            "assetUri": "https://therealtoxicdev.gallerycdn.vsassets.io/extensions/therealtoxicdev/toxics-rpc/1.0.6/1640983344223",
            "fallbackAssetUri": "https://therealtoxicdev.gallery.vsassets.io/_apis/public/gallery/publisher/TheRealToxicDev/extension/toxics-rpc/1.0.6/assetbyname"
        },
        {
            "version": "1.0.5",
            "flags": "validated",
            "lastUpdated": "2021-12-31T13:42:46.493Z",
            "files": [
                {
                    "assetType": "Microsoft.VisualStudio.Code.Manifest",
                    "source": "https://therealtoxicdev.gallerycdn.vsassets.io/extensions/therealtoxicdev/toxics-rpc/1.0.5/1640958028908/Microsoft.VisualStudio.Code.Manifest"
                },
                {
                    "assetType": "Microsoft.VisualStudio.Services.Content.Details",
                    "source": "https://therealtoxicdev.gallerycdn.vsassets.io/extensions/therealtoxicdev/toxics-rpc/1.0.5/1640958028908/Microsoft.VisualStudio.Services.Content.Details"
                },
                {
                    "assetType": "Microsoft.VisualStudio.Services.Content.License",
                    "source": "https://therealtoxicdev.gallerycdn.vsassets.io/extensions/therealtoxicdev/toxics-rpc/1.0.5/1640958028908/Microsoft.VisualStudio.Services.Content.License"
                },
                {
                    "assetType": "Microsoft.VisualStudio.Services.Icons.Default",
                    "source": "https://therealtoxicdev.gallerycdn.vsassets.io/extensions/therealtoxicdev/toxics-rpc/1.0.5/1640958028908/Microsoft.VisualStudio.Services.Icons.Default"
                },
                {
                    "assetType": "Microsoft.VisualStudio.Services.Icons.Small",
                    "source": "https://therealtoxicdev.gallerycdn.vsassets.io/extensions/therealtoxicdev/toxics-rpc/1.0.5/1640958028908/Microsoft.VisualStudio.Services.Icons.Small"
                },
                {
                    "assetType": "Microsoft.VisualStudio.Services.VsixManifest",
                    "source": "https://therealtoxicdev.gallerycdn.vsassets.io/extensions/therealtoxicdev/toxics-rpc/1.0.5/1640958028908/Microsoft.VisualStudio.Services.VsixManifest"
                },
                {
                    "assetType": "Microsoft.VisualStudio.Services.VSIXPackage",
                    "source": "https://therealtoxicdev.gallerycdn.vsassets.io/extensions/therealtoxicdev/toxics-rpc/1.0.5/1640958028908/Microsoft.VisualStudio.Services.VSIXPackage"
                }
            ],
            "properties": [
                {
                    "key": "Microsoft.VisualStudio.Services.Branding.Color",
                    "value": "#5865F2"
                },
                {
                    "key": "Microsoft.VisualStudio.Services.Branding.Theme",
                    "value": "dark"
                },
                {
                    "key": "Microsoft.VisualStudio.Services.Links.Getstarted",
                    "value": "https://github.com/TheRealToxicDev/Toxics-RPC.git"
                },
                {
                    "key": "Microsoft.VisualStudio.Services.Links.Support",
                    "value": "https://github.com/TheRealToxicDev/Toxics-RPC/issues"
                },
                {
                    "key": "Microsoft.VisualStudio.Services.Links.Learn",
                    "value": "https://github.com/TheRealToxicDev/Toxics-RPC#readme"
                },
                {
                    "key": "Microsoft.VisualStudio.Services.Links.Source",
                    "value": "https://github.com/TheRealToxicDev/Toxics-RPC.git"
                },
                {
                    "key": "Microsoft.VisualStudio.Services.Links.GitHub",
                    "value": "https://github.com/TheRealToxicDev/Toxics-RPC.git"
                },
                {
                    "key": "Microsoft.VisualStudio.Code.Engine",
                    "value": "^1.59.0"
                },
                {
                    "key": "Microsoft.VisualStudio.Services.GitHubFlavoredMarkdown",
                    "value": "true"
                },
                {
                    "key": "Microsoft.VisualStudio.Code.ExtensionDependencies",
                    "value": ""
                },
                {
                    "key": "Microsoft.VisualStudio.Code.ExtensionPack",
                    "value": ""
                },
                {
                    "key": "Microsoft.VisualStudio.Code.LocalizedLanguages",
                    "value": ""
                },
                {
                    "key": "Microsoft.VisualStudio.Code.ExtensionKind",
                    "value": "ui,workspace"
                }
            ],
            "assetUri": "https://therealtoxicdev.gallerycdn.vsassets.io/extensions/therealtoxicdev/toxics-rpc/1.0.5/1640958028908",
            "fallbackAssetUri": "https://therealtoxicdev.gallery.vsassets.io/_apis/public/gallery/publisher/TheRealToxicDev/extension/toxics-rpc/1.0.5/assetbyname"
        },
        {
            "version": "1.0.4",
            "flags": "validated",
            "lastUpdated": "2021-12-31T13:34:36.263Z",
            "files": [
                {
                    "assetType": "Microsoft.VisualStudio.Code.Manifest",
                    "source": "https://therealtoxicdev.gallerycdn.vsassets.io/extensions/therealtoxicdev/toxics-rpc/1.0.4/1640957536753/Microsoft.VisualStudio.Code.Manifest"
                },
                {
                    "assetType": "Microsoft.VisualStudio.Services.Content.Details",
                    "source": "https://therealtoxicdev.gallerycdn.vsassets.io/extensions/therealtoxicdev/toxics-rpc/1.0.4/1640957536753/Microsoft.VisualStudio.Services.Content.Details"
                },
                {
                    "assetType": "Microsoft.VisualStudio.Services.Content.License",
                    "source": "https://therealtoxicdev.gallerycdn.vsassets.io/extensions/therealtoxicdev/toxics-rpc/1.0.4/1640957536753/Microsoft.VisualStudio.Services.Content.License"
                },
                {
                    "assetType": "Microsoft.VisualStudio.Services.Icons.Default",
                    "source": "https://therealtoxicdev.gallerycdn.vsassets.io/extensions/therealtoxicdev/toxics-rpc/1.0.4/1640957536753/Microsoft.VisualStudio.Services.Icons.Default"
                },
                {
                    "assetType": "Microsoft.VisualStudio.Services.Icons.Small",
                    "source": "https://therealtoxicdev.gallerycdn.vsassets.io/extensions/therealtoxicdev/toxics-rpc/1.0.4/1640957536753/Microsoft.VisualStudio.Services.Icons.Small"
                },
                {
                    "assetType": "Microsoft.VisualStudio.Services.VsixManifest",
                    "source": "https://therealtoxicdev.gallerycdn.vsassets.io/extensions/therealtoxicdev/toxics-rpc/1.0.4/1640957536753/Microsoft.VisualStudio.Services.VsixManifest"
                },
                {
                    "assetType": "Microsoft.VisualStudio.Services.VSIXPackage",
                    "source": "https://therealtoxicdev.gallerycdn.vsassets.io/extensions/therealtoxicdev/toxics-rpc/1.0.4/1640957536753/Microsoft.VisualStudio.Services.VSIXPackage"
                }
            ],
            "properties": [
                {
                    "key": "Microsoft.VisualStudio.Services.Branding.Color",
                    "value": "#5865F2"
                },
                {
                    "key": "Microsoft.VisualStudio.Services.Branding.Theme",
                    "value": "dark"
                },
                {
                    "key": "Microsoft.VisualStudio.Services.Links.Getstarted",
                    "value": "https://github.com/TheRealToxicDev/Toxics-RPC.git"
                },
                {
                    "key": "Microsoft.VisualStudio.Services.Links.Support",
                    "value": "https://github.com/TheRealToxicDev/Toxics-RPC/issues"
                },
                {
                    "key": "Microsoft.VisualStudio.Services.Links.Learn",
                    "value": "https://github.com/TheRealToxicDev/Toxics-RPC#readme"
                },
                {
                    "key": "Microsoft.VisualStudio.Services.Links.Source",
                    "value": "https://github.com/TheRealToxicDev/Toxics-RPC.git"
                },
                {
                    "key": "Microsoft.VisualStudio.Services.Links.GitHub",
                    "value": "https://github.com/TheRealToxicDev/Toxics-RPC.git"
                },
                {
                    "key": "Microsoft.VisualStudio.Code.Engine",
                    "value": "^1.59.0"
                },
                {
                    "key": "Microsoft.VisualStudio.Services.GitHubFlavoredMarkdown",
                    "value": "true"
                },
                {
                    "key": "Microsoft.VisualStudio.Code.ExtensionDependencies",
                    "value": ""
                },
                {
                    "key": "Microsoft.VisualStudio.Code.ExtensionPack",
                    "value": ""
                },
                {
                    "key": "Microsoft.VisualStudio.Code.LocalizedLanguages",
                    "value": ""
                },
                {
                    "key": "Microsoft.VisualStudio.Code.ExtensionKind",
                    "value": "ui,workspace"
                }
            ],
            "assetUri": "https://therealtoxicdev.gallerycdn.vsassets.io/extensions/therealtoxicdev/toxics-rpc/1.0.4/1640957536753",
            "fallbackAssetUri": "https://therealtoxicdev.gallery.vsassets.io/_apis/public/gallery/publisher/TheRealToxicDev/extension/toxics-rpc/1.0.4/assetbyname"
        },
        {
            "version": "1.0.3",
            "flags": "validated",
            "lastUpdated": "2021-12-31T13:12:04.1Z",
            "files": [
                {
                    "assetType": "Microsoft.VisualStudio.Code.Manifest",
                    "source": "https://therealtoxicdev.gallerycdn.vsassets.io/extensions/therealtoxicdev/toxics-rpc/1.0.3/1640956184650/Microsoft.VisualStudio.Code.Manifest"
                },
                {
                    "assetType": "Microsoft.VisualStudio.Services.Content.Details",
                    "source": "https://therealtoxicdev.gallerycdn.vsassets.io/extensions/therealtoxicdev/toxics-rpc/1.0.3/1640956184650/Microsoft.VisualStudio.Services.Content.Details"
                },
                {
                    "assetType": "Microsoft.VisualStudio.Services.Content.License",
                    "source": "https://therealtoxicdev.gallerycdn.vsassets.io/extensions/therealtoxicdev/toxics-rpc/1.0.3/1640956184650/Microsoft.VisualStudio.Services.Content.License"
                },
                {
                    "assetType": "Microsoft.VisualStudio.Services.Icons.Default",
                    "source": "https://therealtoxicdev.gallerycdn.vsassets.io/extensions/therealtoxicdev/toxics-rpc/1.0.3/1640956184650/Microsoft.VisualStudio.Services.Icons.Default"
                },
                {
                    "assetType": "Microsoft.VisualStudio.Services.Icons.Small",
                    "source": "https://therealtoxicdev.gallerycdn.vsassets.io/extensions/therealtoxicdev/toxics-rpc/1.0.3/1640956184650/Microsoft.VisualStudio.Services.Icons.Small"
                },
                {
                    "assetType": "Microsoft.VisualStudio.Services.VsixManifest",
                    "source": "https://therealtoxicdev.gallerycdn.vsassets.io/extensions/therealtoxicdev/toxics-rpc/1.0.3/1640956184650/Microsoft.VisualStudio.Services.VsixManifest"
                },
                {
                    "assetType": "Microsoft.VisualStudio.Services.VSIXPackage",
                    "source": "https://therealtoxicdev.gallerycdn.vsassets.io/extensions/therealtoxicdev/toxics-rpc/1.0.3/1640956184650/Microsoft.VisualStudio.Services.VSIXPackage"
                }
            ],
            "properties": [
                {
                    "key": "Microsoft.VisualStudio.Services.Branding.Color",
                    "value": "#5865F2"
                },
                {
                    "key": "Microsoft.VisualStudio.Services.Branding.Theme",
                    "value": "dark"
                },
                {
                    "key": "Microsoft.VisualStudio.Services.Links.Getstarted",
                    "value": "https://github.com/TheRealToxicDev/Toxics-RPC.git"
                },
                {
                    "key": "Microsoft.VisualStudio.Services.Links.Support",
                    "value": "https://github.com/TheRealToxicDev/Toxics-RPC/issues"
                },
                {
                    "key": "Microsoft.VisualStudio.Services.Links.Learn",
                    "value": "https://github.com/TheRealToxicDev/Toxics-RPC#readme"
                },
                {
                    "key": "Microsoft.VisualStudio.Services.Links.Source",
                    "value": "https://github.com/TheRealToxicDev/Toxics-RPC.git"
                },
                {
                    "key": "Microsoft.VisualStudio.Services.Links.GitHub",
                    "value": "https://github.com/TheRealToxicDev/Toxics-RPC.git"
                },
                {
                    "key": "Microsoft.VisualStudio.Code.Engine",
                    "value": "^1.59.0"
                },
                {
                    "key": "Microsoft.VisualStudio.Services.GitHubFlavoredMarkdown",
                    "value": "true"
                },
                {
                    "key": "Microsoft.VisualStudio.Code.ExtensionDependencies",
                    "value": ""
                },
                {
                    "key": "Microsoft.VisualStudio.Code.ExtensionPack",
                    "value": ""
                },
                {
                    "key": "Microsoft.VisualStudio.Code.LocalizedLanguages",
                    "value": ""
                },
                {
                    "key": "Microsoft.VisualStudio.Code.ExtensionKind",
                    "value": "ui,workspace"
                }
            ],
            "assetUri": "https://therealtoxicdev.gallerycdn.vsassets.io/extensions/therealtoxicdev/toxics-rpc/1.0.3/1640956184650",
            "fallbackAssetUri": "https://therealtoxicdev.gallery.vsassets.io/_apis/public/gallery/publisher/TheRealToxicDev/extension/toxics-rpc/1.0.3/assetbyname"
        },
        {
            "version": "1.0.2",
            "flags": "validated",
            "lastUpdated": "2021-12-31T12:09:07.333Z",
            "files": [
                {
                    "assetType": "Microsoft.VisualStudio.Code.Manifest",
                    "source": "https://therealtoxicdev.gallerycdn.vsassets.io/extensions/therealtoxicdev/toxics-rpc/1.0.2/1640952409750/Microsoft.VisualStudio.Code.Manifest"
                },
                {
                    "assetType": "Microsoft.VisualStudio.Services.Content.Details",
                    "source": "https://therealtoxicdev.gallerycdn.vsassets.io/extensions/therealtoxicdev/toxics-rpc/1.0.2/1640952409750/Microsoft.VisualStudio.Services.Content.Details"
                },
                {
                    "assetType": "Microsoft.VisualStudio.Services.Content.License",
                    "source": "https://therealtoxicdev.gallerycdn.vsassets.io/extensions/therealtoxicdev/toxics-rpc/1.0.2/1640952409750/Microsoft.VisualStudio.Services.Content.License"
                },
                {
                    "assetType": "Microsoft.VisualStudio.Services.Icons.Default",
                    "source": "https://therealtoxicdev.gallerycdn.vsassets.io/extensions/therealtoxicdev/toxics-rpc/1.0.2/1640952409750/Microsoft.VisualStudio.Services.Icons.Default"
                },
                {
                    "assetType": "Microsoft.VisualStudio.Services.Icons.Small",
                    "source": "https://therealtoxicdev.gallerycdn.vsassets.io/extensions/therealtoxicdev/toxics-rpc/1.0.2/1640952409750/Microsoft.VisualStudio.Services.Icons.Small"
                },
                {
                    "assetType": "Microsoft.VisualStudio.Services.VsixManifest",
                    "source": "https://therealtoxicdev.gallerycdn.vsassets.io/extensions/therealtoxicdev/toxics-rpc/1.0.2/1640952409750/Microsoft.VisualStudio.Services.VsixManifest"
                },
                {
                    "assetType": "Microsoft.VisualStudio.Services.VSIXPackage",
                    "source": "https://therealtoxicdev.gallerycdn.vsassets.io/extensions/therealtoxicdev/toxics-rpc/1.0.2/1640952409750/Microsoft.VisualStudio.Services.VSIXPackage"
                }
            ],
            "properties": [
                {
                    "key": "Microsoft.VisualStudio.Services.Branding.Color",
                    "value": "#5865F2"
                },
                {
                    "key": "Microsoft.VisualStudio.Services.Branding.Theme",
                    "value": "dark"
                },
                {
                    "key": "Microsoft.VisualStudio.Services.Links.Getstarted",
                    "value": "https://github.com/TheRealToxicDev/Toxics-RPC.git"
                },
                {
                    "key": "Microsoft.VisualStudio.Services.Links.Support",
                    "value": "https://github.com/TheRealToxicDev/Toxics-RPC/issues"
                },
                {
                    "key": "Microsoft.VisualStudio.Services.Links.Learn",
                    "value": "https://github.com/TheRealToxicDev/Toxics-RPC#readme"
                },
                {
                    "key": "Microsoft.VisualStudio.Services.Links.Source",
                    "value": "https://github.com/TheRealToxicDev/Toxics-RPC.git"
                },
                {
                    "key": "Microsoft.VisualStudio.Services.Links.GitHub",
                    "value": "https://github.com/TheRealToxicDev/Toxics-RPC.git"
                },
                {
                    "key": "Microsoft.VisualStudio.Code.Engine",
                    "value": "^1.59.0"
                },
                {
                    "key": "Microsoft.VisualStudio.Services.GitHubFlavoredMarkdown",
                    "value": "true"
                },
                {
                    "key": "Microsoft.VisualStudio.Code.ExtensionDependencies",
                    "value": ""
                },
                {
                    "key": "Microsoft.VisualStudio.Code.ExtensionPack",
                    "value": ""
                },
                {
                    "key": "Microsoft.VisualStudio.Code.LocalizedLanguages",
                    "value": ""
                },
                {
                    "key": "Microsoft.VisualStudio.Code.ExtensionKind",
                    "value": "ui,workspace"
                }
            ],
            "assetUri": "https://therealtoxicdev.gallerycdn.vsassets.io/extensions/therealtoxicdev/toxics-rpc/1.0.2/1640952409750",
            "fallbackAssetUri": "https://therealtoxicdev.gallery.vsassets.io/_apis/public/gallery/publisher/TheRealToxicDev/extension/toxics-rpc/1.0.2/assetbyname"
        },
        {
            "version": "1.0.1",
            "flags": "validated",
            "lastUpdated": "2021-12-31T11:35:07.29Z",
            "files": [
                {
                    "assetType": "Microsoft.VisualStudio.Code.Manifest",
                    "source": "https://therealtoxicdev.gallerycdn.vsassets.io/extensions/therealtoxicdev/toxics-rpc/1.0.1/1640950370739/Microsoft.VisualStudio.Code.Manifest"
                },
                {
                    "assetType": "Microsoft.VisualStudio.Services.Content.Details",
                    "source": "https://therealtoxicdev.gallerycdn.vsassets.io/extensions/therealtoxicdev/toxics-rpc/1.0.1/1640950370739/Microsoft.VisualStudio.Services.Content.Details"
                },
                {
                    "assetType": "Microsoft.VisualStudio.Services.Content.License",
                    "source": "https://therealtoxicdev.gallerycdn.vsassets.io/extensions/therealtoxicdev/toxics-rpc/1.0.1/1640950370739/Microsoft.VisualStudio.Services.Content.License"
                },
                {
                    "assetType": "Microsoft.VisualStudio.Services.Icons.Default",
                    "source": "https://therealtoxicdev.gallerycdn.vsassets.io/extensions/therealtoxicdev/toxics-rpc/1.0.1/1640950370739/Microsoft.VisualStudio.Services.Icons.Default"
                },
                {
                    "assetType": "Microsoft.VisualStudio.Services.Icons.Small",
                    "source": "https://therealtoxicdev.gallerycdn.vsassets.io/extensions/therealtoxicdev/toxics-rpc/1.0.1/1640950370739/Microsoft.VisualStudio.Services.Icons.Small"
                },
                {
                    "assetType": "Microsoft.VisualStudio.Services.VsixManifest",
                    "source": "https://therealtoxicdev.gallerycdn.vsassets.io/extensions/therealtoxicdev/toxics-rpc/1.0.1/1640950370739/Microsoft.VisualStudio.Services.VsixManifest"
                },
                {
                    "assetType": "Microsoft.VisualStudio.Services.VSIXPackage",
                    "source": "https://therealtoxicdev.gallerycdn.vsassets.io/extensions/therealtoxicdev/toxics-rpc/1.0.1/1640950370739/Microsoft.VisualStudio.Services.VSIXPackage"
                }
            ],
            "properties": [
                {
                    "key": "Microsoft.VisualStudio.Services.Branding.Color",
                    "value": "#5865F2"
                },
                {
                    "key": "Microsoft.VisualStudio.Services.Branding.Theme",
                    "value": "dark"
                },
                {
                    "key": "Microsoft.VisualStudio.Services.Links.Getstarted",
                    "value": "https://github.com/TheRealToxicDev/Toxics-RPC.git"
                },
                {
                    "key": "Microsoft.VisualStudio.Services.Links.Support",
                    "value": "https://github.com/TheRealToxicDev/Toxics-RPC/issues"
                },
                {
                    "key": "Microsoft.VisualStudio.Services.Links.Learn",
                    "value": "https://github.com/TheRealToxicDev/Toxics-RPC#readme"
                },
                {
                    "key": "Microsoft.VisualStudio.Services.Links.Source",
                    "value": "https://github.com/TheRealToxicDev/Toxics-RPC.git"
                },
                {
                    "key": "Microsoft.VisualStudio.Services.Links.GitHub",
                    "value": "https://github.com/TheRealToxicDev/Toxics-RPC.git"
                },
                {
                    "key": "Microsoft.VisualStudio.Code.Engine",
                    "value": "^1.59.0"
                },
                {
                    "key": "Microsoft.VisualStudio.Services.GitHubFlavoredMarkdown",
                    "value": "true"
                },
                {
                    "key": "Microsoft.VisualStudio.Code.ExtensionDependencies",
                    "value": ""
                },
                {
                    "key": "Microsoft.VisualStudio.Code.ExtensionPack",
                    "value": ""
                },
                {
                    "key": "Microsoft.VisualStudio.Code.LocalizedLanguages",
                    "value": ""
                },
                {
                    "key": "Microsoft.VisualStudio.Code.ExtensionKind",
                    "value": "ui,workspace"
                }
            ],
            "assetUri": "https://therealtoxicdev.gallerycdn.vsassets.io/extensions/therealtoxicdev/toxics-rpc/1.0.1/1640950370739",
            "fallbackAssetUri": "https://therealtoxicdev.gallery.vsassets.io/_apis/public/gallery/publisher/TheRealToxicDev/extension/toxics-rpc/1.0.1/assetbyname"
        },
        {
            "version": "1.0.0",
            "flags": "validated",
            "lastUpdated": "2021-12-31T10:58:41Z",
            "files": [
                {
                    "assetType": "Microsoft.VisualStudio.Code.Manifest",
                    "source": "https://therealtoxicdev.gallerycdn.vsassets.io/extensions/therealtoxicdev/toxics-rpc/1.0.0/1640948182039/Microsoft.VisualStudio.Code.Manifest"
                },
                {
                    "assetType": "Microsoft.VisualStudio.Services.Content.Details",
                    "source": "https://therealtoxicdev.gallerycdn.vsassets.io/extensions/therealtoxicdev/toxics-rpc/1.0.0/1640948182039/Microsoft.VisualStudio.Services.Content.Details"
                },
                {
                    "assetType": "Microsoft.VisualStudio.Services.Content.License",
                    "source": "https://therealtoxicdev.gallerycdn.vsassets.io/extensions/therealtoxicdev/toxics-rpc/1.0.0/1640948182039/Microsoft.VisualStudio.Services.Content.License"
                },
                {
                    "assetType": "Microsoft.VisualStudio.Services.Icons.Default",
                    "source": "https://therealtoxicdev.gallerycdn.vsassets.io/extensions/therealtoxicdev/toxics-rpc/1.0.0/1640948182039/Microsoft.VisualStudio.Services.Icons.Default"
                },
                {
                    "assetType": "Microsoft.VisualStudio.Services.Icons.Small",
                    "source": "https://therealtoxicdev.gallerycdn.vsassets.io/extensions/therealtoxicdev/toxics-rpc/1.0.0/1640948182039/Microsoft.VisualStudio.Services.Icons.Small"
                },
                {
                    "assetType": "Microsoft.VisualStudio.Services.VsixManifest",
                    "source": "https://therealtoxicdev.gallerycdn.vsassets.io/extensions/therealtoxicdev/toxics-rpc/1.0.0/1640948182039/Microsoft.VisualStudio.Services.VsixManifest"
                },
                {
                    "assetType": "Microsoft.VisualStudio.Services.VSIXPackage",
                    "source": "https://therealtoxicdev.gallerycdn.vsassets.io/extensions/therealtoxicdev/toxics-rpc/1.0.0/1640948182039/Microsoft.VisualStudio.Services.VSIXPackage"
                }
            ],
            "properties": [
                {
                    "key": "Microsoft.VisualStudio.Services.Branding.Color",
                    "value": "#5865F2"
                },
                {
                    "key": "Microsoft.VisualStudio.Services.Branding.Theme",
                    "value": "dark"
                },
                {
                    "key": "Microsoft.VisualStudio.Services.Links.Getstarted",
                    "value": "https://github.com/TheRealToxicDev/Toxics-RPC.git"
                },
                {
                    "key": "Microsoft.VisualStudio.Services.Links.Support",
                    "value": "https://github.com/TheRealToxicDev/Toxics-RPC/issues"
                },
                {
                    "key": "Microsoft.VisualStudio.Services.Links.Learn",
                    "value": "https://github.com/TheRealToxicDev/Toxics-RPC#readme"
                },
                {
                    "key": "Microsoft.VisualStudio.Services.Links.Source",
                    "value": "https://github.com/TheRealToxicDev/Toxics-RPC.git"
                },
                {
                    "key": "Microsoft.VisualStudio.Services.Links.GitHub",
                    "value": "https://github.com/TheRealToxicDev/Toxics-RPC.git"
                },
                {
                    "key": "Microsoft.VisualStudio.Code.Engine",
                    "value": "^1.59.0"
                },
                {
                    "key": "Microsoft.VisualStudio.Services.GitHubFlavoredMarkdown",
                    "value": "true"
                },
                {
                    "key": "Microsoft.VisualStudio.Code.ExtensionDependencies",
                    "value": ""
                },
                {
                    "key": "Microsoft.VisualStudio.Code.ExtensionPack",
                    "value": ""
                },
                {
                    "key": "Microsoft.VisualStudio.Code.LocalizedLanguages",
                    "value": ""
                },
                {
                    "key": "Microsoft.VisualStudio.Code.ExtensionKind",
                    "value": "ui,workspace"
                }
            ],
            "assetUri": "https://therealtoxicdev.gallerycdn.vsassets.io/extensions/therealtoxicdev/toxics-rpc/1.0.0/1640948182039",
            "fallbackAssetUri": "https://therealtoxicdev.gallery.vsassets.io/_apis/public/gallery/publisher/TheRealToxicDev/extension/toxics-rpc/1.0.0/assetbyname"
        }
    ],
    "categories": [
        "Visualization"
    ],
    "tags": [
        "discord",
        "game status",
        "presence",
        "rich",
        "rich presence",
        "rpc",
        "vscode"
    ],
    "statistics": [
        {
            "statisticName": "install",
            "value": 1281.0
        },
        {
            "statisticName": "averagerating",
            "value": 5.0
        },
        {
            "statisticName": "ratingcount",
            "value": 1.0
        },
        {
            "statisticName": "trendingdaily",
            "value": 0.0
        },
        {
            "statisticName": "trendingmonthly",
            "value": 4.765625
        },
        {
            "statisticName": "trendingweekly",
            "value": 0.546875
        },
        {
            "statisticName": "updateCount",
            "value": 176.0
        },
        {
            "statisticName": "weightedRating",
            "value": 4.457458844826611
        },
        {
            "statisticName": "downloadCount",
            "value": 24.0
        }
    ],
    "installationTargets": [
        {
            "target": "Microsoft.VisualStudio.Code",
            "targetVersion": ""
        }
    ],
    "deploymentType": 0
}