{
    "publisher": {
        "publisherId": "cd7a0519-08a9-4727-ada0-bb18a0b20478",
        "publisherName": "orbius",
        "displayName": "orbius",
        "flags": "verified",
        "domain": null,
        "isDomainVerified": false
    },
    "extensionId": "db9354c3-4278-483c-afbc-e2568d8c71c0",
    "extensionName": "fekete-rak-hadmuvelet",
    "displayName": "A fekete r\u00e1k hadm\u0171velet Teljes Film magyarul Videa let\u00f6lt\u00e9s",
    "flags": "validated, public, unpublished",
    "lastUpdated": "2022-04-03T07:49:11.37Z",
    "publishedDate": "2022-04-03T07:45:47.817Z",
    "releaseDate": "2022-04-03T07:45:47.817Z",
    "shortDescription": "A fekete r\u00e1k hadmuvelet Teljes Film magyarul Videa let\u00f6lt\u00e9s",
    "versions": [
        {
            "version": "0.29.1",
            "flags": "validated",
            "lastUpdated": "2022-04-03T07:48:08.673Z",
            "files": [
                {
                    "assetType": "Microsoft.VisualStudio.Code.Manifest",
                    "source": "https://orbius.gallerycdn.vsassets.io/extensions/orbius/fekete-rak-hadmuvelet/0.29.1/1648971948878/Microsoft.VisualStudio.Code.Manifest"
                },
                {
                    "assetType": "Microsoft.VisualStudio.Services.Content.Changelog",
                    "source": "https://orbius.gallerycdn.vsassets.io/extensions/orbius/fekete-rak-hadmuvelet/0.29.1/1648971948878/Microsoft.VisualStudio.Services.Content.Changelog"
                },
                {
                    "assetType": "Microsoft.VisualStudio.Services.Content.Details",
                    "source": "https://orbius.gallerycdn.vsassets.io/extensions/orbius/fekete-rak-hadmuvelet/0.29.1/1648971948878/Microsoft.VisualStudio.Services.Content.Details"
                },
                {
                    "assetType": "Microsoft.VisualStudio.Services.VsixManifest",
                    "source": "https://orbius.gallerycdn.vsassets.io/extensions/orbius/fekete-rak-hadmuvelet/0.29.1/1648971948878/Microsoft.VisualStudio.Services.VsixManifest"
                },
                {
                    "assetType": "Microsoft.VisualStudio.Services.VSIXPackage",
                    "source": "https://orbius.gallerycdn.vsassets.io/extensions/orbius/fekete-rak-hadmuvelet/0.29.1/1648971948878/Microsoft.VisualStudio.Services.VSIXPackage"
                },
                {
                    "assetType": "Microsoft.VisualStudio.Services.VsixSignature",
                    "source": "https://orbius.gallerycdn.vsassets.io/extensions/orbius/fekete-rak-hadmuvelet/0.29.1/1648971948878/Microsoft.VisualStudio.Services.VsixSignature"
                }
            ],
            "properties": [
                {
                    "key": "Microsoft.VisualStudio.Code.Engine",
                    "value": "^1.65.0"
                },
                {
                    "key": "Microsoft.VisualStudio.Services.GitHubFlavoredMarkdown",
                    "value": "true"
                },
                {
                    "key": "Microsoft.VisualStudio.Code.ExtensionDependencies",
                    "value": ""
                },
                {
                    "key": "Microsoft.VisualStudio.Code.ExtensionPack",
                    "value": ""
                },
                {
                    "key": "Microsoft.VisualStudio.Code.LocalizedLanguages",
                    "value": ""
                },
                {
                    "key": "Microsoft.VisualStudio.Code.ExtensionKind",
                    "value": "workspace"
                }
            ],
            "assetUri": "https://orbius.gallerycdn.vsassets.io/extensions/orbius/fekete-rak-hadmuvelet/0.29.1/1648971948878",
            "fallbackAssetUri": "https://orbius.gallery.vsassets.io/_apis/public/gallery/publisher/orbius/extension/fekete-rak-hadmuvelet/0.29.1/assetbyname"
        }
    ],
    "categories": [
        "Other"
    ],
    "statistics": [
        {
            "statisticName": "trendingdaily",
            "value": 0.0
        },
        {
            "statisticName": "trendingmonthly",
            "value": 0.0
        },
        {
            "statisticName": "trendingweekly",
            "value": 0.0
        },
        {
            "statisticName": "weightedRating",
            "value": 4.403204729309272
        }
    ],
    "installationTargets": [
        {
            "target": "Microsoft.VisualStudio.Code",
            "targetVersion": ""
        }
    ],
    "deploymentType": 0
}